memex/__init__.py
memex/translators/__init__.py
memex/translators/igor/__init__.py
memex/translators/igor/binarywave.py
memex/translators/igor/igorpy.py
memex/translators/igor/packed.py
memex/translators/igor/script.py
memex/translators/igor/struct.py
memex/translators/igor/util.py
memex/translators/igor/record/__init__.py
memex/translators/igor/record/base.py
memex/translators/igor/record/folder.py
memex/translators/igor/record/history.py
memex/translators/igor/record/packedfile.py
memex/translators/igor/record/procedure.py
memex/translators/igor/record/variables.py
memex/translators/igor/record/wave.py
sci_memex-0.0.3.dist-info/METADATA
sci_memex-0.0.3.dist-info/WHEEL
sci_memex-0.0.3.dist-info/top_level.txt
sci_memex-0.0.3.dist-info/RECORD
