Metadata-Version: 2.1
Name: sci-memex
Version: 0.0.3
Summary: Scientific Data Memex
Home-page: https://github.com/m3-learning/memex
Author: Joshua C. Agar
Author-email: jca92@drexel.edu
License: BSD-3-Clause
Classifier: Programming Language :: Python :: 3
Classifier: License :: OSI Approved :: BSD License
Classifier: Operating System :: OS Independent
Requires-Python: >=3.6
